execcelery/__init__.py
execcelery/connection.py
execcelery/producer.py
execcelery/queuecatch.py
execcelery/queuecontrol.py
exec_celery-0.0.21.dist-info/LICENSE
exec_celery-0.0.21.dist-info/METADATA
exec_celery-0.0.21.dist-info/WHEEL
exec_celery-0.0.21.dist-info/top_level.txt
exec_celery-0.0.21.dist-info/RECORD
