Metadata-Version: 2.1
Name: exec-celery
Version: 0.0.21
Summary: Celery handler.
Home-page: https://github.com/Supplayer/exec_celery.git
Author: Supplayer
Author-email: x254724521@hotmail.com
License: UNKNOWN
Platform: UNKNOWN
Classifier: Programming Language :: Python :: 3
Classifier: License :: OSI Approved :: MIT License
Classifier: Operating System :: OS Independent
Requires-Python: >=3.6
License-File: LICENSE
Requires-Dist: celery[gevent,msgpack,zstd]
